{
  "pilots": [
    {
      "name": "JohnDoe",
      "hours": 19392,
      "flights": 9636,
      "rank": "Captain"
    },
    {
      "name": "JaneSmith",
      "hours": 19361,
      "flights": 9753,
      "rank": "First Officer"
    },
    {
      "name": "AlexPilot",
      "hours": 19363,
      "flights": 9559,
      "rank": "Second Officer"
    },
    {
      "name": "KakoytoPilot",
      "hours": 48211,
      "flights": 9726,
      "rank": "Captain"
    }
  ],
  "last_updated": "2026-03-31T15:44:07.742419"
}