{
  "pilots": [
    {
      "name": "JohnDoe",
      "hours": 5660,
      "flights": 2788,
      "rank": "Captain"
    },
    {
      "name": "JaneSmith",
      "hours": 5645,
      "flights": 2853,
      "rank": "First Officer"
    },
    {
      "name": "AlexPilot",
      "hours": 5648,
      "flights": 2772,
      "rank": "Second Officer"
    },
    {
      "name": "KakoytoPilot",
      "hours": 34604,
      "flights": 2926,
      "rank": "Captain"
    }
  ],
  "last_updated": "2025-09-28T05:36:42.566040"
}