{
  "pilots": [
    {
      "name": "JohnDoe",
      "hours": 18948,
      "flights": 9387,
      "rank": "Captain"
    },
    {
      "name": "JaneSmith",
      "hours": 18909,
      "flights": 9523,
      "rank": "First Officer"
    },
    {
      "name": "AlexPilot",
      "hours": 18926,
      "flights": 9323,
      "rank": "Second Officer"
    },
    {
      "name": "KakoytoPilot",
      "hours": 47749,
      "flights": 9504,
      "rank": "Captain"
    }
  ],
  "last_updated": "2026-03-22T15:45:46.260611"
}