{
  "pilots": [
    {
      "name": "JohnDoe",
      "hours": 19860,
      "flights": 9879,
      "rank": "Captain"
    },
    {
      "name": "JaneSmith",
      "hours": 19848,
      "flights": 9998,
      "rank": "First Officer"
    },
    {
      "name": "AlexPilot",
      "hours": 19848,
      "flights": 9804,
      "rank": "Second Officer"
    },
    {
      "name": "KakoytoPilot",
      "hours": 48705,
      "flights": 9980,
      "rank": "Captain"
    }
  ],
  "last_updated": "2026-04-11T15:01:32.859979"
}