{
  "pilots": [
    {
      "name": "JohnDoe",
      "hours": 11921,
      "flights": 5874,
      "rank": "Captain"
    },
    {
      "name": "JaneSmith",
      "hours": 11841,
      "flights": 5994,
      "rank": "First Officer"
    },
    {
      "name": "AlexPilot",
      "hours": 11898,
      "flights": 5874,
      "rank": "Second Officer"
    },
    {
      "name": "KakoytoPilot",
      "hours": 40809,
      "flights": 6029,
      "rank": "Captain"
    }
  ],
  "last_updated": "2025-12-10T10:14:09.404319"
}