{
  "pilots": [
    {
      "name": "JohnDoe",
      "hours": 14306,
      "flights": 7113,
      "rank": "Captain"
    },
    {
      "name": "JaneSmith",
      "hours": 14258,
      "flights": 7187,
      "rank": "First Officer"
    },
    {
      "name": "AlexPilot",
      "hours": 14278,
      "flights": 7034,
      "rank": "Second Officer"
    },
    {
      "name": "KakoytoPilot",
      "hours": 43149,
      "flights": 7262,
      "rank": "Captain"
    }
  ],
  "last_updated": "2026-01-08T11:39:18.733367"
}