{
  "pilots": [
    {
      "name": "JohnDoe",
      "hours": 19783,
      "flights": 9836,
      "rank": "Captain"
    },
    {
      "name": "JaneSmith",
      "hours": 19775,
      "flights": 9959,
      "rank": "First Officer"
    },
    {
      "name": "AlexPilot",
      "hours": 19771,
      "flights": 9759,
      "rank": "Second Officer"
    },
    {
      "name": "KakoytoPilot",
      "hours": 48622,
      "flights": 9944,
      "rank": "Captain"
    }
  ],
  "last_updated": "2026-04-09T19:57:46.425676"
}