{
  "pilots": [
    {
      "name": "JohnDoe",
      "hours": 8668,
      "flights": 4250,
      "rank": "Captain"
    },
    {
      "name": "JaneSmith",
      "hours": 8671,
      "flights": 4369,
      "rank": "First Officer"
    },
    {
      "name": "AlexPilot",
      "hours": 8668,
      "flights": 4302,
      "rank": "Second Officer"
    },
    {
      "name": "KakoytoPilot",
      "hours": 37615,
      "flights": 4410,
      "rank": "Captain"
    }
  ],
  "last_updated": "2025-11-02T04:14:40.631625"
}