{
  "pilots": [
    {
      "name": "JohnDoe",
      "hours": 1986,
      "flights": 978,
      "rank": "Captain"
    },
    {
      "name": "JaneSmith",
      "hours": 1927,
      "flights": 964,
      "rank": "First Officer"
    },
    {
      "name": "AlexPilot",
      "hours": 1950,
      "flights": 942,
      "rank": "Second Officer"
    },
    {
      "name": "KakoytoPilot",
      "hours": 30876,
      "flights": 1072,
      "rank": "Captain"
    }
  ],
  "last_updated": "2025-08-16T08:43:12.165071"
}