{
  "pilots": [
    {
      "name": "JohnDoe",
      "hours": 2031,
      "flights": 1011,
      "rank": "Captain"
    },
    {
      "name": "JaneSmith",
      "hours": 1974,
      "flights": 985,
      "rank": "First Officer"
    },
    {
      "name": "AlexPilot",
      "hours": 1989,
      "flights": 962,
      "rank": "Second Officer"
    },
    {
      "name": "KakoytoPilot",
      "hours": 30925,
      "flights": 1095,
      "rank": "Captain"
    }
  ],
  "last_updated": "2025-08-16T21:09:49.008922"
}