{
  "pilots": [
    {
      "name": "JohnDoe",
      "hours": 18278,
      "flights": 9071,
      "rank": "Captain"
    },
    {
      "name": "JaneSmith",
      "hours": 18260,
      "flights": 9192,
      "rank": "First Officer"
    },
    {
      "name": "AlexPilot",
      "hours": 18266,
      "flights": 8969,
      "rank": "Second Officer"
    },
    {
      "name": "KakoytoPilot",
      "hours": 47119,
      "flights": 9191,
      "rank": "Captain"
    }
  ],
  "last_updated": "2026-03-11T01:08:21.182558"
}