{
  "pilots": [
    {
      "name": "JohnDoe",
      "hours": 6143,
      "flights": 3019,
      "rank": "Captain"
    },
    {
      "name": "JaneSmith",
      "hours": 6107,
      "flights": 3080,
      "rank": "First Officer"
    },
    {
      "name": "AlexPilot",
      "hours": 6135,
      "flights": 3000,
      "rank": "Second Officer"
    },
    {
      "name": "KakoytoPilot",
      "hours": 35104,
      "flights": 3147,
      "rank": "Captain"
    }
  ],
  "last_updated": "2025-10-03T14:38:35.943769"
}