{
  "pilots": [
    {
      "name": "JohnDoe",
      "hours": 2208,
      "flights": 1094,
      "rank": "Captain"
    },
    {
      "name": "JaneSmith",
      "hours": 2173,
      "flights": 1071,
      "rank": "First Officer"
    },
    {
      "name": "AlexPilot",
      "hours": 2167,
      "flights": 1058,
      "rank": "Second Officer"
    },
    {
      "name": "KakoytoPilot",
      "hours": 31115,
      "flights": 1165,
      "rank": "Captain"
    }
  ],
  "last_updated": "2025-08-19T04:41:42.825736"
}