{
  "pilots": [
    {
      "name": "JohnDoe",
      "hours": 792,
      "flights": 371,
      "rank": "Captain"
    },
    {
      "name": "JaneSmith",
      "hours": 764,
      "flights": 388,
      "rank": "First Officer"
    },
    {
      "name": "AlexPilot",
      "hours": 775,
      "flights": 362,
      "rank": "Second Officer"
    },
    {
      "name": "KakoytoPilot",
      "hours": 29686,
      "flights": 462,
      "rank": "Captain"
    }
  ],
  "last_updated": "2025-08-01T22:11:32.765850"
}