{
  "pilots": [
    {
      "name": "JohnDoe",
      "hours": 3501,
      "flights": 1738,
      "rank": "Captain"
    },
    {
      "name": "JaneSmith",
      "hours": 3454,
      "flights": 1754,
      "rank": "First Officer"
    },
    {
      "name": "AlexPilot",
      "hours": 3452,
      "flights": 1698,
      "rank": "Second Officer"
    },
    {
      "name": "KakoytoPilot",
      "hours": 32431,
      "flights": 1846,
      "rank": "Captain"
    }
  ],
  "last_updated": "2025-09-03T10:11:14.466318"
}