{
  "pilots": [
    {
      "name": "JohnDoe",
      "hours": 1988,
      "flights": 982,
      "rank": "Captain"
    },
    {
      "name": "JaneSmith",
      "hours": 1930,
      "flights": 965,
      "rank": "First Officer"
    },
    {
      "name": "AlexPilot",
      "hours": 1953,
      "flights": 942,
      "rank": "Second Officer"
    },
    {
      "name": "KakoytoPilot",
      "hours": 30880,
      "flights": 1075,
      "rank": "Captain"
    }
  ],
  "last_updated": "2025-08-16T09:37:02.383327"
}