{
  "pilots": [
    {
      "name": "JohnDoe",
      "hours": 12846,
      "flights": 6331,
      "rank": "Captain"
    },
    {
      "name": "JaneSmith",
      "hours": 12780,
      "flights": 6446,
      "rank": "First Officer"
    },
    {
      "name": "AlexPilot",
      "hours": 12824,
      "flights": 6309,
      "rank": "Second Officer"
    },
    {
      "name": "KakoytoPilot",
      "hours": 41706,
      "flights": 6522,
      "rank": "Captain"
    }
  ],
  "last_updated": "2025-12-21T13:02:37.134220"
}