{
  "pilots": [
    {
      "name": "JohnDoe",
      "hours": 18633,
      "flights": 9250,
      "rank": "Captain"
    },
    {
      "name": "JaneSmith",
      "hours": 18604,
      "flights": 9378,
      "rank": "First Officer"
    },
    {
      "name": "AlexPilot",
      "hours": 18625,
      "flights": 9156,
      "rank": "Second Officer"
    },
    {
      "name": "KakoytoPilot",
      "hours": 47466,
      "flights": 9353,
      "rank": "Captain"
    }
  ],
  "last_updated": "2026-03-17T07:48:05.735805"
}