{
  "pilots": [
    {
      "name": "JohnDoe",
      "hours": 20270,
      "flights": 10082,
      "rank": "Captain"
    },
    {
      "name": "JaneSmith",
      "hours": 20278,
      "flights": 10183,
      "rank": "First Officer"
    },
    {
      "name": "AlexPilot",
      "hours": 20257,
      "flights": 10011,
      "rank": "Second Officer"
    },
    {
      "name": "KakoytoPilot",
      "hours": 49124,
      "flights": 10201,
      "rank": "Captain"
    }
  ],
  "last_updated": "2026-04-22T14:54:32.750460"
}