{
  "pilots": [
    {
      "name": "JohnDoe",
      "hours": 21479,
      "flights": 10702,
      "rank": "Captain"
    },
    {
      "name": "JaneSmith",
      "hours": 21461,
      "flights": 10795,
      "rank": "First Officer"
    },
    {
      "name": "AlexPilot",
      "hours": 21455,
      "flights": 10590,
      "rank": "Second Officer"
    },
    {
      "name": "KakoytoPilot",
      "hours": 50305,
      "flights": 10801,
      "rank": "Captain"
    }
  ],
  "last_updated": "2026-06-09T16:14:57.993970"
}