{
  "pilots": [
    {
      "name": "JohnDoe",
      "hours": 17092,
      "flights": 8491,
      "rank": "Captain"
    },
    {
      "name": "JaneSmith",
      "hours": 17036,
      "flights": 8570,
      "rank": "First Officer"
    },
    {
      "name": "AlexPilot",
      "hours": 17077,
      "flights": 8403,
      "rank": "Second Officer"
    },
    {
      "name": "KakoytoPilot",
      "hours": 45952,
      "flights": 8605,
      "rank": "Captain"
    }
  ],
  "last_updated": "2026-02-18T14:01:03.810347"
}