{
  "pilots": [
    {
      "name": "JohnDoe",
      "hours": 2752,
      "flights": 1352,
      "rank": "Captain"
    },
    {
      "name": "JaneSmith",
      "hours": 2717,
      "flights": 1369,
      "rank": "First Officer"
    },
    {
      "name": "AlexPilot",
      "hours": 2727,
      "flights": 1348,
      "rank": "Second Officer"
    },
    {
      "name": "KakoytoPilot",
      "hours": 31675,
      "flights": 1450,
      "rank": "Captain"
    }
  ],
  "last_updated": "2025-08-25T16:44:47.758164"
}