{
  "pilots": [
    {
      "name": "JohnDoe",
      "hours": 15219,
      "flights": 7582,
      "rank": "Captain"
    },
    {
      "name": "JaneSmith",
      "hours": 15169,
      "flights": 7647,
      "rank": "First Officer"
    },
    {
      "name": "AlexPilot",
      "hours": 15218,
      "flights": 7487,
      "rank": "Second Officer"
    },
    {
      "name": "KakoytoPilot",
      "hours": 44077,
      "flights": 7700,
      "rank": "Captain"
    }
  ],
  "last_updated": "2026-01-19T20:14:18.419124"
}