{
  "pilots": [
    {
      "name": "JohnDoe",
      "hours": 22439,
      "flights": 11185,
      "rank": "Captain"
    },
    {
      "name": "JaneSmith",
      "hours": 22408,
      "flights": 11288,
      "rank": "First Officer"
    },
    {
      "name": "AlexPilot",
      "hours": 22443,
      "flights": 11039,
      "rank": "Second Officer"
    },
    {
      "name": "KakoytoPilot",
      "hours": 51263,
      "flights": 11288,
      "rank": "Captain"
    }
  ],
  "last_updated": "2026-07-22T16:13:58.853387"
}