{
  "pilots": [
    {
      "name": "JohnDoe",
      "hours": 17284,
      "flights": 8579,
      "rank": "Captain"
    },
    {
      "name": "JaneSmith",
      "hours": 17214,
      "flights": 8672,
      "rank": "First Officer"
    },
    {
      "name": "AlexPilot",
      "hours": 17258,
      "flights": 8490,
      "rank": "Second Officer"
    },
    {
      "name": "KakoytoPilot",
      "hours": 46139,
      "flights": 8700,
      "rank": "Captain"
    }
  ],
  "last_updated": "2026-02-21T18:57:28.837048"
}