{
  "pilots": [
    {
      "name": "JohnDoe",
      "hours": 19869,
      "flights": 9885,
      "rank": "Captain"
    },
    {
      "name": "JaneSmith",
      "hours": 19860,
      "flights": 10003,
      "rank": "First Officer"
    },
    {
      "name": "AlexPilot",
      "hours": 19861,
      "flights": 9807,
      "rank": "Second Officer"
    },
    {
      "name": "KakoytoPilot",
      "hours": 48718,
      "flights": 9985,
      "rank": "Captain"
    }
  ],
  "last_updated": "2026-04-11T18:29:34.766147"
}