{
  "pilots": [
    {
      "name": "JohnDoe",
      "hours": 1850,
      "flights": 908,
      "rank": "Captain"
    },
    {
      "name": "JaneSmith",
      "hours": 1811,
      "flights": 901,
      "rank": "First Officer"
    },
    {
      "name": "AlexPilot",
      "hours": 1810,
      "flights": 878,
      "rank": "Second Officer"
    },
    {
      "name": "KakoytoPilot",
      "hours": 30736,
      "flights": 998,
      "rank": "Captain"
    }
  ],
  "last_updated": "2025-08-14T18:50:15.624387"
}