{
  "pilots": [
    {
      "name": "JohnDoe",
      "hours": 11508,
      "flights": 5689,
      "rank": "Captain"
    },
    {
      "name": "JaneSmith",
      "hours": 11439,
      "flights": 5805,
      "rank": "First Officer"
    },
    {
      "name": "AlexPilot",
      "hours": 11512,
      "flights": 5692,
      "rank": "Second Officer"
    },
    {
      "name": "KakoytoPilot",
      "hours": 40425,
      "flights": 5837,
      "rank": "Captain"
    }
  ],
  "last_updated": "2025-12-05T18:15:13.800440"
}