{
  "pilots": [
    {
      "name": "JohnDoe",
      "hours": 8086,
      "flights": 3945,
      "rank": "Captain"
    },
    {
      "name": "JaneSmith",
      "hours": 8051,
      "flights": 4068,
      "rank": "First Officer"
    },
    {
      "name": "AlexPilot",
      "hours": 8068,
      "flights": 3986,
      "rank": "Second Officer"
    },
    {
      "name": "KakoytoPilot",
      "hours": 37018,
      "flights": 4083,
      "rank": "Captain"
    }
  ],
  "last_updated": "2025-10-25T22:09:22.627668"
}