{
  "pilots": [
    {
      "name": "JohnDoe",
      "hours": 4847,
      "flights": 2379,
      "rank": "Captain"
    },
    {
      "name": "JaneSmith",
      "hours": 4791,
      "flights": 2395,
      "rank": "First Officer"
    },
    {
      "name": "AlexPilot",
      "hours": 4820,
      "flights": 2350,
      "rank": "Second Officer"
    },
    {
      "name": "KakoytoPilot",
      "hours": 33765,
      "flights": 2491,
      "rank": "Captain"
    }
  ],
  "last_updated": "2025-09-18T13:01:19.525518"
}