{
  "pilots": [
    {
      "name": "JohnDoe",
      "hours": 5270,
      "flights": 2593,
      "rank": "Captain"
    },
    {
      "name": "JaneSmith",
      "hours": 5240,
      "flights": 2641,
      "rank": "First Officer"
    },
    {
      "name": "AlexPilot",
      "hours": 5254,
      "flights": 2566,
      "rank": "Second Officer"
    },
    {
      "name": "KakoytoPilot",
      "hours": 34205,
      "flights": 2722,
      "rank": "Captain"
    }
  ],
  "last_updated": "2025-09-23T14:40:37.764641"
}