{
  "pilots": [
    {
      "name": "JohnDoe",
      "hours": 18747,
      "flights": 9299,
      "rank": "Captain"
    },
    {
      "name": "JaneSmith",
      "hours": 18705,
      "flights": 9434,
      "rank": "First Officer"
    },
    {
      "name": "AlexPilot",
      "hours": 18735,
      "flights": 9210,
      "rank": "Second Officer"
    },
    {
      "name": "KakoytoPilot",
      "hours": 47575,
      "flights": 9409,
      "rank": "Captain"
    }
  ],
  "last_updated": "2026-03-19T16:12:21.943496"
}