{
  "pilots": [
    {
      "name": "JohnDoe",
      "hours": 11563,
      "flights": 5719,
      "rank": "Captain"
    },
    {
      "name": "JaneSmith",
      "hours": 11493,
      "flights": 5837,
      "rank": "First Officer"
    },
    {
      "name": "AlexPilot",
      "hours": 11561,
      "flights": 5719,
      "rank": "Second Officer"
    },
    {
      "name": "KakoytoPilot",
      "hours": 40482,
      "flights": 5866,
      "rank": "Captain"
    }
  ],
  "last_updated": "2025-12-06T09:36:26.423448"
}