{
  "pilots": [
    {
      "name": "JohnDoe",
      "hours": 19924,
      "flights": 9911,
      "rank": "Captain"
    },
    {
      "name": "JaneSmith",
      "hours": 19924,
      "flights": 10028,
      "rank": "First Officer"
    },
    {
      "name": "AlexPilot",
      "hours": 19912,
      "flights": 9835,
      "rank": "Second Officer"
    },
    {
      "name": "KakoytoPilot",
      "hours": 48769,
      "flights": 10009,
      "rank": "Captain"
    }
  ],
  "last_updated": "2026-04-12T19:32:15.203243"
}