{
  "pilots": [
    {
      "name": "JohnDoe",
      "hours": 2635,
      "flights": 1286,
      "rank": "Captain"
    },
    {
      "name": "JaneSmith",
      "hours": 2594,
      "flights": 1304,
      "rank": "First Officer"
    },
    {
      "name": "AlexPilot",
      "hours": 2616,
      "flights": 1274,
      "rank": "Second Officer"
    },
    {
      "name": "KakoytoPilot",
      "hours": 31538,
      "flights": 1392,
      "rank": "Captain"
    }
  ],
  "last_updated": "2025-08-24T06:15:52.810978"
}