{
  "pilots": [
    {
      "name": "JohnDoe",
      "hours": 22473,
      "flights": 11203,
      "rank": "Captain"
    },
    {
      "name": "JaneSmith",
      "hours": 22443,
      "flights": 11303,
      "rank": "First Officer"
    },
    {
      "name": "AlexPilot",
      "hours": 22478,
      "flights": 11057,
      "rank": "Second Officer"
    },
    {
      "name": "KakoytoPilot",
      "hours": 51297,
      "flights": 11301,
      "rank": "Captain"
    }
  ],
  "last_updated": "2026-07-23T21:32:12.910222"
}