{
  "pilots": [
    {
      "name": "JohnDoe",
      "hours": 18967,
      "flights": 9398,
      "rank": "Captain"
    },
    {
      "name": "JaneSmith",
      "hours": 18934,
      "flights": 9533,
      "rank": "First Officer"
    },
    {
      "name": "AlexPilot",
      "hours": 18953,
      "flights": 9334,
      "rank": "Second Officer"
    },
    {
      "name": "KakoytoPilot",
      "hours": 47774,
      "flights": 9517,
      "rank": "Captain"
    }
  ],
  "last_updated": "2026-03-22T22:15:17.913318"
}