{
  "pilots": [
    {
      "name": "JohnDoe",
      "hours": 13068,
      "flights": 6456,
      "rank": "Captain"
    },
    {
      "name": "JaneSmith",
      "hours": 12997,
      "flights": 6548,
      "rank": "First Officer"
    },
    {
      "name": "AlexPilot",
      "hours": 13055,
      "flights": 6431,
      "rank": "Second Officer"
    },
    {
      "name": "KakoytoPilot",
      "hours": 41925,
      "flights": 6632,
      "rank": "Captain"
    }
  ],
  "last_updated": "2025-12-24T06:53:50.184935"
}