{
  "pilots": [
    {
      "name": "JohnDoe",
      "hours": 3965,
      "flights": 1951,
      "rank": "Captain"
    },
    {
      "name": "JaneSmith",
      "hours": 3914,
      "flights": 1972,
      "rank": "First Officer"
    },
    {
      "name": "AlexPilot",
      "hours": 3943,
      "flights": 1922,
      "rank": "Second Officer"
    },
    {
      "name": "KakoytoPilot",
      "hours": 32913,
      "flights": 2075,
      "rank": "Captain"
    }
  ],
  "last_updated": "2025-09-08T17:09:37.723619"
}