{
  "pilots": [
    {
      "name": "JohnDoe",
      "hours": 15435,
      "flights": 7688,
      "rank": "Captain"
    },
    {
      "name": "JaneSmith",
      "hours": 15375,
      "flights": 7745,
      "rank": "First Officer"
    },
    {
      "name": "AlexPilot",
      "hours": 15433,
      "flights": 7592,
      "rank": "Second Officer"
    },
    {
      "name": "KakoytoPilot",
      "hours": 44272,
      "flights": 7795,
      "rank": "Captain"
    }
  ],
  "last_updated": "2026-01-22T15:51:50.827405"
}