{
  "pilots": [
    {
      "name": "JohnDoe",
      "hours": 14931,
      "flights": 7431,
      "rank": "Captain"
    },
    {
      "name": "JaneSmith",
      "hours": 14895,
      "flights": 7498,
      "rank": "First Officer"
    },
    {
      "name": "AlexPilot",
      "hours": 14923,
      "flights": 7348,
      "rank": "Second Officer"
    },
    {
      "name": "KakoytoPilot",
      "hours": 43788,
      "flights": 7552,
      "rank": "Captain"
    }
  ],
  "last_updated": "2026-01-16T07:42:17.896998"
}