{
  "pilots": [
    {
      "name": "JohnDoe",
      "hours": 2852,
      "flights": 1398,
      "rank": "Captain"
    },
    {
      "name": "JaneSmith",
      "hours": 2818,
      "flights": 1415,
      "rank": "First Officer"
    },
    {
      "name": "AlexPilot",
      "hours": 2814,
      "flights": 1388,
      "rank": "Second Officer"
    },
    {
      "name": "KakoytoPilot",
      "hours": 31783,
      "flights": 1496,
      "rank": "Captain"
    }
  ],
  "last_updated": "2025-08-26T18:44:55.726024"
}