{
  "pilots": [
    {
      "name": "JohnDoe",
      "hours": 7181,
      "flights": 3506,
      "rank": "Captain"
    },
    {
      "name": "JaneSmith",
      "hours": 7128,
      "flights": 3634,
      "rank": "First Officer"
    },
    {
      "name": "AlexPilot",
      "hours": 7173,
      "flights": 3499,
      "rank": "Second Officer"
    },
    {
      "name": "KakoytoPilot",
      "hours": 36119,
      "flights": 3628,
      "rank": "Captain"
    }
  ],
  "last_updated": "2025-10-15T10:42:25.709109"
}