{
  "pilots": [
    {
      "name": "JohnDoe",
      "hours": 13639,
      "flights": 6761,
      "rank": "Captain"
    },
    {
      "name": "JaneSmith",
      "hours": 13586,
      "flights": 6848,
      "rank": "First Officer"
    },
    {
      "name": "AlexPilot",
      "hours": 13619,
      "flights": 6729,
      "rank": "Second Officer"
    },
    {
      "name": "KakoytoPilot",
      "hours": 42489,
      "flights": 6927,
      "rank": "Captain"
    }
  ],
  "last_updated": "2025-12-31T06:20:19.499746"
}