{
  "pilots": [
    {
      "name": "JohnDoe",
      "hours": 20106,
      "flights": 10013,
      "rank": "Captain"
    },
    {
      "name": "JaneSmith",
      "hours": 20109,
      "flights": 10123,
      "rank": "First Officer"
    },
    {
      "name": "AlexPilot",
      "hours": 20100,
      "flights": 9927,
      "rank": "Second Officer"
    },
    {
      "name": "KakoytoPilot",
      "hours": 48957,
      "flights": 10126,
      "rank": "Captain"
    }
  ],
  "last_updated": "2026-04-18T10:31:12.522087"
}