{
  "pilots": [
    {
      "name": "JohnDoe",
      "hours": 3732,
      "flights": 1844,
      "rank": "Captain"
    },
    {
      "name": "JaneSmith",
      "hours": 3678,
      "flights": 1863,
      "rank": "First Officer"
    },
    {
      "name": "AlexPilot",
      "hours": 3707,
      "flights": 1817,
      "rank": "Second Officer"
    },
    {
      "name": "KakoytoPilot",
      "hours": 32669,
      "flights": 1952,
      "rank": "Captain"
    }
  ],
  "last_updated": "2025-09-06T03:05:36.429537"
}