{
  "pilots": [
    {
      "name": "JohnDoe",
      "hours": 13278,
      "flights": 6553,
      "rank": "Captain"
    },
    {
      "name": "JaneSmith",
      "hours": 13205,
      "flights": 6648,
      "rank": "First Officer"
    },
    {
      "name": "AlexPilot",
      "hours": 13257,
      "flights": 6529,
      "rank": "Second Officer"
    },
    {
      "name": "KakoytoPilot",
      "hours": 42131,
      "flights": 6737,
      "rank": "Captain"
    }
  ],
  "last_updated": "2025-12-26T16:13:49.098359"
}