{
  "pilots": [
    {
      "name": "JohnDoe",
      "hours": 10133,
      "flights": 4982,
      "rank": "Captain"
    },
    {
      "name": "JaneSmith",
      "hours": 10089,
      "flights": 5122,
      "rank": "First Officer"
    },
    {
      "name": "AlexPilot",
      "hours": 10123,
      "flights": 5045,
      "rank": "Second Officer"
    },
    {
      "name": "KakoytoPilot",
      "hours": 39109,
      "flights": 5145,
      "rank": "Captain"
    }
  ],
  "last_updated": "2025-11-19T16:47:23.035958"
}