{
  "pilots": [
    {
      "name": "JohnDoe",
      "hours": 10838,
      "flights": 5351,
      "rank": "Captain"
    },
    {
      "name": "JaneSmith",
      "hours": 10783,
      "flights": 5465,
      "rank": "First Officer"
    },
    {
      "name": "AlexPilot",
      "hours": 10841,
      "flights": 5388,
      "rank": "Second Officer"
    },
    {
      "name": "KakoytoPilot",
      "hours": 39782,
      "flights": 5515,
      "rank": "Captain"
    }
  ],
  "last_updated": "2025-11-27T20:37:10.267542"
}