{
  "pilots": [
    {
      "name": "JohnDoe",
      "hours": 1438,
      "flights": 696,
      "rank": "Captain"
    },
    {
      "name": "JaneSmith",
      "hours": 1403,
      "flights": 700,
      "rank": "First Officer"
    },
    {
      "name": "AlexPilot",
      "hours": 1394,
      "flights": 679,
      "rank": "Second Officer"
    },
    {
      "name": "KakoytoPilot",
      "hours": 30322,
      "flights": 800,
      "rank": "Captain"
    }
  ],
  "last_updated": "2025-08-09T21:10:06.384335"
}