{
  "pilots": [
    {
      "name": "JohnDoe",
      "hours": 7714,
      "flights": 3768,
      "rank": "Captain"
    },
    {
      "name": "JaneSmith",
      "hours": 7688,
      "flights": 3896,
      "rank": "First Officer"
    },
    {
      "name": "AlexPilot",
      "hours": 7708,
      "flights": 3778,
      "rank": "Second Officer"
    },
    {
      "name": "KakoytoPilot",
      "hours": 36640,
      "flights": 3897,
      "rank": "Captain"
    }
  ],
  "last_updated": "2025-10-21T18:15:27.875963"
}