{
  "pilots": [
    {
      "name": "JohnDoe",
      "hours": 9808,
      "flights": 4819,
      "rank": "Captain"
    },
    {
      "name": "JaneSmith",
      "hours": 9762,
      "flights": 4953,
      "rank": "First Officer"
    },
    {
      "name": "AlexPilot",
      "hours": 9798,
      "flights": 4884,
      "rank": "Second Officer"
    },
    {
      "name": "KakoytoPilot",
      "hours": 38767,
      "flights": 4973,
      "rank": "Captain"
    }
  ],
  "last_updated": "2025-11-15T16:11:36.011789"
}