{
  "pilots": [
    {
      "name": "JohnDoe",
      "hours": 10437,
      "flights": 5131,
      "rank": "Captain"
    },
    {
      "name": "JaneSmith",
      "hours": 10398,
      "flights": 5276,
      "rank": "First Officer"
    },
    {
      "name": "AlexPilot",
      "hours": 10437,
      "flights": 5203,
      "rank": "Second Officer"
    },
    {
      "name": "KakoytoPilot",
      "hours": 39408,
      "flights": 5306,
      "rank": "Captain"
    }
  ],
  "last_updated": "2025-11-23T07:33:55.422657"
}