{
  "pilots": [
    {
      "name": "JohnDoe",
      "hours": 8735,
      "flights": 4277,
      "rank": "Captain"
    },
    {
      "name": "JaneSmith",
      "hours": 8735,
      "flights": 4403,
      "rank": "First Officer"
    },
    {
      "name": "AlexPilot",
      "hours": 8739,
      "flights": 4326,
      "rank": "Second Officer"
    },
    {
      "name": "KakoytoPilot",
      "hours": 37689,
      "flights": 4446,
      "rank": "Captain"
    }
  ],
  "last_updated": "2025-11-02T22:09:43.118950"
}