{
  "pilots": [
    {
      "name": "JohnDoe",
      "hours": 2782,
      "flights": 1364,
      "rank": "Captain"
    },
    {
      "name": "JaneSmith",
      "hours": 2745,
      "flights": 1386,
      "rank": "First Officer"
    },
    {
      "name": "AlexPilot",
      "hours": 2755,
      "flights": 1363,
      "rank": "Second Officer"
    },
    {
      "name": "KakoytoPilot",
      "hours": 31712,
      "flights": 1463,
      "rank": "Captain"
    }
  ],
  "last_updated": "2025-08-26T00:54:12.657821"
}