{
  "pilots": [
    {
      "name": "JohnDoe",
      "hours": 9927,
      "flights": 4890,
      "rank": "Captain"
    },
    {
      "name": "JaneSmith",
      "hours": 9888,
      "flights": 5013,
      "rank": "First Officer"
    },
    {
      "name": "AlexPilot",
      "hours": 9926,
      "flights": 4946,
      "rank": "Second Officer"
    },
    {
      "name": "KakoytoPilot",
      "hours": 38903,
      "flights": 5040,
      "rank": "Captain"
    }
  ],
  "last_updated": "2025-11-17T05:40:42.997701"
}