{
  "pilots": [
    {
      "name": "JohnDoe",
      "hours": 4983,
      "flights": 2449,
      "rank": "Captain"
    },
    {
      "name": "JaneSmith",
      "hours": 4921,
      "flights": 2469,
      "rank": "First Officer"
    },
    {
      "name": "AlexPilot",
      "hours": 4959,
      "flights": 2424,
      "rank": "Second Officer"
    },
    {
      "name": "KakoytoPilot",
      "hours": 33913,
      "flights": 2572,
      "rank": "Captain"
    }
  ],
  "last_updated": "2025-09-20T06:14:29.873709"
}