{
  "pilots": [
    {
      "name": "JohnDoe",
      "hours": 16159,
      "flights": 8052,
      "rank": "Captain"
    },
    {
      "name": "JaneSmith",
      "hours": 16104,
      "flights": 8110,
      "rank": "First Officer"
    },
    {
      "name": "AlexPilot",
      "hours": 16149,
      "flights": 7951,
      "rank": "Second Officer"
    },
    {
      "name": "KakoytoPilot",
      "hours": 45029,
      "flights": 8163,
      "rank": "Captain"
    }
  ],
  "last_updated": "2026-02-01T14:20:43.100755"
}