{
  "pilots": [
    {
      "name": "JohnDoe",
      "hours": 4431,
      "flights": 2163,
      "rank": "Captain"
    },
    {
      "name": "JaneSmith",
      "hours": 4393,
      "flights": 2196,
      "rank": "First Officer"
    },
    {
      "name": "AlexPilot",
      "hours": 4417,
      "flights": 2138,
      "rank": "Second Officer"
    },
    {
      "name": "KakoytoPilot",
      "hours": 33360,
      "flights": 2290,
      "rank": "Captain"
    }
  ],
  "last_updated": "2025-09-13T22:08:26.899213"
}