{
  "pilots": [
    {
      "name": "JohnDoe",
      "hours": 8556,
      "flights": 4199,
      "rank": "Captain"
    },
    {
      "name": "JaneSmith",
      "hours": 8550,
      "flights": 4301,
      "rank": "First Officer"
    },
    {
      "name": "AlexPilot",
      "hours": 8546,
      "flights": 4240,
      "rank": "Second Officer"
    },
    {
      "name": "KakoytoPilot",
      "hours": 37499,
      "flights": 4355,
      "rank": "Captain"
    }
  ],
  "last_updated": "2025-10-31T17:38:36.857327"
}