{
  "pilots": [
    {
      "name": "JohnDoe",
      "hours": 12406,
      "flights": 6114,
      "rank": "Captain"
    },
    {
      "name": "JaneSmith",
      "hours": 12330,
      "flights": 6229,
      "rank": "First Officer"
    },
    {
      "name": "AlexPilot",
      "hours": 12389,
      "flights": 6090,
      "rank": "Second Officer"
    },
    {
      "name": "KakoytoPilot",
      "hours": 41276,
      "flights": 6264,
      "rank": "Captain"
    }
  ],
  "last_updated": "2025-12-16T06:20:07.980077"
}