{
  "pilots": [
    {
      "name": "JohnDoe",
      "hours": 20052,
      "flights": 9984,
      "rank": "Captain"
    },
    {
      "name": "JaneSmith",
      "hours": 20057,
      "flights": 10093,
      "rank": "First Officer"
    },
    {
      "name": "AlexPilot",
      "hours": 20048,
      "flights": 9897,
      "rank": "Second Officer"
    },
    {
      "name": "KakoytoPilot",
      "hours": 48897,
      "flights": 10093,
      "rank": "Captain"
    }
  ],
  "last_updated": "2026-04-16T21:34:20.429326"
}