{
  "pilots": [
    {
      "name": "JohnDoe",
      "hours": 5649,
      "flights": 2788,
      "rank": "Captain"
    },
    {
      "name": "JaneSmith",
      "hours": 5633,
      "flights": 2849,
      "rank": "First Officer"
    },
    {
      "name": "AlexPilot",
      "hours": 5637,
      "flights": 2767,
      "rank": "Second Officer"
    },
    {
      "name": "KakoytoPilot",
      "hours": 34596,
      "flights": 2923,
      "rank": "Captain"
    }
  ],
  "last_updated": "2025-09-28T03:26:49.015885"
}