{
  "pilots": [
    {
      "name": "JohnDoe",
      "hours": 3423,
      "flights": 1688,
      "rank": "Captain"
    },
    {
      "name": "JaneSmith",
      "hours": 3376,
      "flights": 1711,
      "rank": "First Officer"
    },
    {
      "name": "AlexPilot",
      "hours": 3379,
      "flights": 1659,
      "rank": "Second Officer"
    },
    {
      "name": "KakoytoPilot",
      "hours": 32348,
      "flights": 1803,
      "rank": "Captain"
    }
  ],
  "last_updated": "2025-09-02T11:33:08.666943"
}