{
  "pilots": [
    {
      "name": "JohnDoe",
      "hours": 10584,
      "flights": 5206,
      "rank": "Captain"
    },
    {
      "name": "JaneSmith",
      "hours": 10546,
      "flights": 5343,
      "rank": "First Officer"
    },
    {
      "name": "AlexPilot",
      "hours": 10578,
      "flights": 5268,
      "rank": "Second Officer"
    },
    {
      "name": "KakoytoPilot",
      "hours": 39536,
      "flights": 5380,
      "rank": "Captain"
    }
  ],
  "last_updated": "2025-11-24T21:11:19.741585"
}