{
  "pilots": [
    {
      "name": "JohnDoe",
      "hours": 11903,
      "flights": 5867,
      "rank": "Captain"
    },
    {
      "name": "JaneSmith",
      "hours": 11821,
      "flights": 5983,
      "rank": "First Officer"
    },
    {
      "name": "AlexPilot",
      "hours": 11877,
      "flights": 5863,
      "rank": "Second Officer"
    },
    {
      "name": "KakoytoPilot",
      "hours": 40789,
      "flights": 6021,
      "rank": "Captain"
    }
  ],
  "last_updated": "2025-12-10T05:42:08.836685"
}