{
  "pilots": [
    {
      "name": "JohnDoe",
      "hours": 21016,
      "flights": 10462,
      "rank": "Captain"
    },
    {
      "name": "JaneSmith",
      "hours": 21014,
      "flights": 10564,
      "rank": "First Officer"
    },
    {
      "name": "AlexPilot",
      "hours": 20993,
      "flights": 10386,
      "rank": "Second Officer"
    },
    {
      "name": "KakoytoPilot",
      "hours": 49846,
      "flights": 10574,
      "rank": "Captain"
    }
  ],
  "last_updated": "2026-05-17T20:56:48.107853"
}