{
  "pilots": [
    {
      "name": "JohnDoe",
      "hours": 12904,
      "flights": 6369,
      "rank": "Captain"
    },
    {
      "name": "JaneSmith",
      "hours": 12841,
      "flights": 6481,
      "rank": "First Officer"
    },
    {
      "name": "AlexPilot",
      "hours": 12886,
      "flights": 6347,
      "rank": "Second Officer"
    },
    {
      "name": "KakoytoPilot",
      "hours": 41759,
      "flights": 6550,
      "rank": "Captain"
    }
  ],
  "last_updated": "2025-12-22T07:17:13.886077"
}