{
  "pilots": [
    {
      "name": "JohnDoe",
      "hours": 5399,
      "flights": 2651,
      "rank": "Captain"
    },
    {
      "name": "JaneSmith",
      "hours": 5366,
      "flights": 2706,
      "rank": "First Officer"
    },
    {
      "name": "AlexPilot",
      "hours": 5367,
      "flights": 2632,
      "rank": "Second Officer"
    },
    {
      "name": "KakoytoPilot",
      "hours": 34334,
      "flights": 2789,
      "rank": "Captain"
    }
  ],
  "last_updated": "2025-09-25T03:12:37.131234"
}