{
  "pilots": [
    {
      "name": "JohnDoe",
      "hours": 9412,
      "flights": 4605,
      "rank": "Captain"
    },
    {
      "name": "JaneSmith",
      "hours": 9391,
      "flights": 4754,
      "rank": "First Officer"
    },
    {
      "name": "AlexPilot",
      "hours": 9414,
      "flights": 4686,
      "rank": "Second Officer"
    },
    {
      "name": "KakoytoPilot",
      "hours": 38361,
      "flights": 4778,
      "rank": "Captain"
    }
  ],
  "last_updated": "2025-11-10T22:39:45.528180"
}