{
  "pilots": [
    {
      "name": "JohnDoe",
      "hours": 19001,
      "flights": 9418,
      "rank": "Captain"
    },
    {
      "name": "JaneSmith",
      "hours": 18964,
      "flights": 9546,
      "rank": "First Officer"
    },
    {
      "name": "AlexPilot",
      "hours": 18981,
      "flights": 9347,
      "rank": "Second Officer"
    },
    {
      "name": "KakoytoPilot",
      "hours": 47803,
      "flights": 9530,
      "rank": "Captain"
    }
  ],
  "last_updated": "2026-03-23T16:46:19.445974"
}