{
  "pilots": [
    {
      "name": "JohnDoe",
      "hours": 7005,
      "flights": 3436,
      "rank": "Captain"
    },
    {
      "name": "JaneSmith",
      "hours": 6954,
      "flights": 3557,
      "rank": "First Officer"
    },
    {
      "name": "AlexPilot",
      "hours": 7018,
      "flights": 3416,
      "rank": "Second Officer"
    },
    {
      "name": "KakoytoPilot",
      "hours": 35941,
      "flights": 3548,
      "rank": "Captain"
    }
  ],
  "last_updated": "2025-10-13T12:22:02.669931"
}