{
  "pilots": [
    {
      "name": "JohnDoe",
      "hours": 8412,
      "flights": 4123,
      "rank": "Captain"
    },
    {
      "name": "JaneSmith",
      "hours": 8406,
      "flights": 4240,
      "rank": "First Officer"
    },
    {
      "name": "AlexPilot",
      "hours": 8414,
      "flights": 4171,
      "rank": "Second Officer"
    },
    {
      "name": "KakoytoPilot",
      "hours": 37360,
      "flights": 4280,
      "rank": "Captain"
    }
  ],
  "last_updated": "2025-10-30T00:55:47.209372"
}