{
  "pilots": [
    {
      "name": "JohnDoe",
      "hours": 17304,
      "flights": 8592,
      "rank": "Captain"
    },
    {
      "name": "JaneSmith",
      "hours": 17242,
      "flights": 8682,
      "rank": "First Officer"
    },
    {
      "name": "AlexPilot",
      "hours": 17280,
      "flights": 8497,
      "rank": "Second Officer"
    },
    {
      "name": "KakoytoPilot",
      "hours": 46164,
      "flights": 8713,
      "rank": "Captain"
    }
  ],
  "last_updated": "2026-02-22T01:14:44.815829"
}