{
  "pilots": [
    {
      "name": "JohnDoe",
      "hours": 482,
      "flights": 218,
      "rank": "Captain"
    },
    {
      "name": "JaneSmith",
      "hours": 453,
      "flights": 220,
      "rank": "First Officer"
    },
    {
      "name": "AlexPilot",
      "hours": 444,
      "flights": 205,
      "rank": "Second Officer"
    },
    {
      "name": "KakoytoPilot",
      "hours": 29374,
      "flights": 310,
      "rank": "Captain"
    }
  ],
  "last_updated": "2025-07-29T04:29:18.010349"
}