{
  "pilots": [
    {
      "name": "JohnDoe",
      "hours": 7585,
      "flights": 3716,
      "rank": "Captain"
    },
    {
      "name": "JaneSmith",
      "hours": 7562,
      "flights": 3839,
      "rank": "First Officer"
    },
    {
      "name": "AlexPilot",
      "hours": 7591,
      "flights": 3706,
      "rank": "Second Officer"
    },
    {
      "name": "KakoytoPilot",
      "hours": 36520,
      "flights": 3840,
      "rank": "Captain"
    }
  ],
  "last_updated": "2025-10-20T08:44:22.256969"
}