{
  "pilots": [
    {
      "name": "JohnDoe",
      "hours": 22191,
      "flights": 11058,
      "rank": "Captain"
    },
    {
      "name": "JaneSmith",
      "hours": 22164,
      "flights": 11165,
      "rank": "First Officer"
    },
    {
      "name": "AlexPilot",
      "hours": 22201,
      "flights": 10913,
      "rank": "Second Officer"
    },
    {
      "name": "KakoytoPilot",
      "hours": 51015,
      "flights": 11146,
      "rank": "Captain"
    }
  ],
  "last_updated": "2026-07-13T23:42:27.936891"
}