{
  "pilots": [
    {
      "name": "JohnDoe",
      "hours": 21242,
      "flights": 10579,
      "rank": "Captain"
    },
    {
      "name": "JaneSmith",
      "hours": 21225,
      "flights": 10679,
      "rank": "First Officer"
    },
    {
      "name": "AlexPilot",
      "hours": 21216,
      "flights": 10492,
      "rank": "Second Officer"
    },
    {
      "name": "KakoytoPilot",
      "hours": 50068,
      "flights": 10679,
      "rank": "Captain"
    }
  ],
  "last_updated": "2026-05-28T05:40:38.180896"
}