{
  "pilots": [
    {
      "name": "JohnDoe",
      "hours": 9920,
      "flights": 4888,
      "rank": "Captain"
    },
    {
      "name": "JaneSmith",
      "hours": 9882,
      "flights": 5007,
      "rank": "First Officer"
    },
    {
      "name": "AlexPilot",
      "hours": 9919,
      "flights": 4944,
      "rank": "Second Officer"
    },
    {
      "name": "KakoytoPilot",
      "hours": 38895,
      "flights": 5037,
      "rank": "Captain"
    }
  ],
  "last_updated": "2025-11-17T03:43:39.497426"
}